portwatch/__init__.py
portwatch/__main__.py
portwatch/actions.py
portwatch/app.py
portwatch/scanner.py
portwatch/widgets/__init__.py
portwatch/widgets/action_modal.py
portwatch/widgets/header.py
portwatch/widgets/port_table.py
portwatch_tui-0.1.0.dist-info/METADATA
portwatch_tui-0.1.0.dist-info/WHEEL
portwatch_tui-0.1.0.dist-info/entry_points.txt
portwatch_tui-0.1.0.dist-info/licenses/LICENSE
portwatch_tui-0.1.0.dist-info/RECORD
