Metadata-Version: 2.4
Name: portwatch-tui
Version: 0.1.0
Summary: A tactical port scanner dashboard for developers
Project-URL: Homepage, https://github.com/MarcusL11/portwatch
Project-URL: Repository, https://github.com/MarcusL11/portwatch
Project-URL: Issues, https://github.com/MarcusL11/portwatch/issues
Author-email: MarcusL11 <marclert@gmail.com>
License: MIT
License-File: LICENSE
Keywords: dashboard,monitoring,network,port,scanner,terminal,tui
Classifier: Development Status :: 3 - Alpha
Classifier: Environment :: Console
Classifier: Intended Audience :: Developers
Classifier: Intended Audience :: System Administrators
Classifier: License :: OSI Approved :: MIT License
Classifier: Operating System :: OS Independent
Classifier: Programming Language :: Python :: 3
Classifier: Programming Language :: Python :: 3.10
Classifier: Programming Language :: Python :: 3.11
Classifier: Programming Language :: Python :: 3.12
Classifier: Topic :: System :: Networking :: Monitoring
Classifier: Topic :: Utilities
Requires-Python: >=3.10
Requires-Dist: psutil>=5.9.0
Requires-Dist: rich>=13.0.0
Requires-Dist: textual>=0.50.0
